setup.cfg
setup.py
sparql_protocol/__init__.py
sparql_protocol/reader.py
sparql_protocol/writer.py
sparql_protocol/test/__init__.py
sparql_protocol/test/test_sparql_protocol.py
surf.sparql_protocol.egg-info/PKG-INFO
surf.sparql_protocol.egg-info/SOURCES.txt
surf.sparql_protocol.egg-info/dependency_links.txt
surf.sparql_protocol.egg-info/entry_points.txt
surf.sparql_protocol.egg-info/requires.txt
surf.sparql_protocol.egg-info/top_level.txt