Metadata-Version: 1.1
Name: surf.sparql-protocol
Version: 1.0.0-r336
Summary: surf SPARQL protocol plugin
Home-page: http://code.google.com/p/surfrdf/
Author: Cosmin Basca
Author-email: cosmin.basca at google.com
License: New BSD SOFTWARE
Keywords: python SPARQL RDF resource mapper
Platform: any
Classifier: Development Status :: 3 - Alpha
Classifier: Intended Audience :: Developers
Classifier: License :: OSI Approved :: BSD License
Classifier: Operating System :: OS Independent
Classifier: Programming Language :: Python :: 2.5
Requires: simplejson
